LICENSE
MANIFEST.in
pyproject.toml
setup.py
recometrics/__init__.py
recometrics/wrapper.h
recometrics/wrapper.pyx
recometrics.egg-info/PKG-INFO
recometrics.egg-info/SOURCES.txt
recometrics.egg-info/dependency_links.txt
recometrics.egg-info/requires.txt
recometrics.egg-info/top_level.txt
src/recometrics.hpp
src/recometrics_instantiated.cpp
src/recometrics_signatures.hpp